ymmsl/__init__.py
ymmsl/checkpoint.py
ymmsl/component.py
ymmsl/configuration.py
ymmsl/document.py
ymmsl/execution.py
ymmsl/identity.py
ymmsl/io.py
ymmsl/model.py
ymmsl/py.typed
ymmsl/settings.py
ymmsl-0.14.0.dist-info/LICENSE
ymmsl-0.14.0.dist-info/METADATA
ymmsl-0.14.0.dist-info/NOTICE
ymmsl-0.14.0.dist-info/WHEEL
ymmsl-0.14.0.dist-info/top_level.txt
ymmsl-0.14.0.dist-info/RECORD
