Metadata-Version: 2.1
Name: ymmsl
Version: 0.14.0
Summary: Python bindings for the YAML version of the Multiscale Modeling and Simulation Language
Home-page: https://github.com/multiscale/ymmsl-python
Author: Lourens Veen
Author-email: l.veen@esciencecenter.nl
License: Apache Software License 2.0
Keywords: yMMSL multiscale modeling simulation YAML
Classifier: Development Status :: 4 - Beta
Classifier: Intended Audience :: Developers
Classifier: License :: OSI Approved :: Apache Software License
Classifier: Natural Language :: English
Classifier: Programming Language :: Python :: 3
Classifier: Programming Language :: Python :: 3.7
Classifier: Programming Language :: Python :: 3.8
Classifier: Programming Language :: Python :: 3.9
Classifier: Programming Language :: Python :: 3.10
Classifier: Programming Language :: Python :: 3.11
Classifier: Programming Language :: Python :: 3.12
Requires-Python: >=3.7, <4
License-File: LICENSE
License-File: NOTICE
Requires-Dist: yatiml<0.12.0,>=0.11.1
